bring_order/__init__.py
bring_order/ai.py
bring_order/bodi.py
bring_order/bogui.py
bring_order/boutils.py
bring_order/boval.py
bring_order/bringorder.py
bring_order/deductive.py
bring_order/inductive.py
bring_order/language_models/en_core_web_sm/__init__.py
bring_order/language_models/en_core_web_sm/en_core_web_sm-3.6.0/LICENSE
bring_order/language_models/en_core_web_sm/en_core_web_sm-3.6.0/LICENSES_SOURCES
bring_order/language_models/en_core_web_sm/en_core_web_sm-3.6.0/README.md
bring_order/language_models/en_core_web_sm/en_core_web_sm-3.6.0/accuracy.json
bring_order/language_models/en_core_web_sm/en_core_web_sm-3.6.0/attribute_ruler/patterns
bring_order/language_models/en_core_web_sm/en_core_web_sm-3.6.0/config.cfg
bring_order/language_models/en_core_web_sm/en_core_web_sm-3.6.0/lemmatizer/lookups/lookups.bin
bring_order/language_models/en_core_web_sm/en_core_web_sm-3.6.0/meta.json
bring_order/language_models/en_core_web_sm/en_core_web_sm-3.6.0/ner/cfg
bring_order/language_models/en_core_web_sm/en_core_web_sm-3.6.0/ner/model
bring_order/language_models/en_core_web_sm/en_core_web_sm-3.6.0/ner/moves
bring_order/language_models/en_core_web_sm/en_core_web_sm-3.6.0/parser/cfg
bring_order/language_models/en_core_web_sm/en_core_web_sm-3.6.0/parser/model
bring_order/language_models/en_core_web_sm/en_core_web_sm-3.6.0/parser/moves
bring_order/language_models/en_core_web_sm/en_core_web_sm-3.6.0/senter/cfg
bring_order/language_models/en_core_web_sm/en_core_web_sm-3.6.0/senter/model
bring_order/language_models/en_core_web_sm/en_core_web_sm-3.6.0/tagger/cfg
bring_order/language_models/en_core_web_sm/en_core_web_sm-3.6.0/tagger/model
bring_order/language_models/en_core_web_sm/en_core_web_sm-3.6.0/tok2vec/cfg
bring_order/language_models/en_core_web_sm/en_core_web_sm-3.6.0/tok2vec/model
bring_order/language_models/en_core_web_sm/en_core_web_sm-3.6.0/tokenizer
bring_order/language_models/en_core_web_sm/en_core_web_sm-3.6.0/vocab/key2row
bring_order-1.0.1.dist-info/LICENSE
bring_order-1.0.1.dist-info/METADATA
bring_order-1.0.1.dist-info/WHEEL
bring_order-1.0.1.dist-info/RECORD
