Metadata-Version: 2.1
Name: bring-order
Version: 1.0.1
Summary: Improved tools for data scientists
Author: BringOrder team
Requires-Python: >=3.8,<4.0
Classifier: Programming Language :: Python :: 3
Classifier: Programming Language :: Python :: 3.8
Classifier: Programming Language :: Python :: 3.9
Classifier: Programming Language :: Python :: 3.10
Classifier: Programming Language :: Python :: 3.11
Requires-Dist: display (>=1.0.0,<2.0.0)
Requires-Dist: invoke (>=2.1.2,<3.0.0)
Requires-Dist: ipyfilechooser (>=0.6.0,<0.7.0)
Requires-Dist: ipywidgets (>=8.0.6,<9.0.0)
Requires-Dist: jupyter-ui-poll (>=0.2.2,<0.3.0)
Requires-Dist: notebook (>=6.5.4,<7.0.0)
Requires-Dist: openai (>=0.27.8,<0.28.0)
Requires-Dist: pandas (>=2.0.3,<3.0.0)
Requires-Dist: python-pptx (>=0.6.21,<0.7.0)
Requires-Dist: requests (>=2.31.0,<3.0.0)
Requires-Dist: scipy (>=1.7.1,<2.0.0)
Requires-Dist: spacy (>=3.6.0,<4.0.0)
